lib/api/__init__.py
lib/api/proxy.py
lib/api/run.py
lib/cpython_loop_3.11.py
lib/cpython_loop_3.12.py
lib/cpython_tasks_3.11.py
lib/cpython_tasks_3.12.py
lib/exception_handler.py
lib/log.py
lib/log_levels.py
lib/rstats/poetry.lock
lib/rstats/pyproject.toml
lib/rstats/rstats/__init__.py
lib/rstats/rstats/avg.py
lib/rstats/rstats/bench.py
lib/rstats/rstats/counter.py
lib/rstats/rstats/format.py
lib/rstats/rstats/prof.py
lib/rstats/rstats/stats.py
lib/rstats/rstats/time.py
lib/rstats/rstats/types.py
lib/stats.py
lib/webloop_pyodide_current.py
lib/webloop_pyodide_old.py
lib/weblooper.py
lib/weblooperBench.1.py
lib/weblooperBench.py
lib/weblooperV1.py
lib/weblooperV10.py
lib/weblooperV11.py
lib/weblooperV2.py
lib/weblooperV3.py
lib/weblooperV4.py
lib/weblooperV5.py
lib/weblooperV6.py
lib/weblooperV7.py
lib/weblooperV8.py
lib/weblooperV9.py
SecretSantaExplained.py
aes.py
bnnmnist.py
cnnmnist.py
dsa.py
elgamal.py
helloworld.py
id3gini.py
indextounitvector.py
kmsurvival.py
lpsolver.py
lpsolverfxp.py
multilateration.py
np_aes.py
np_bnnmnist.py
np_cnnmnist.py
np_id3gini.py
np_lpsolver.py
np_lpsolverfxp.py
np_onewayhashchains.py
oneliners.py
onewayhashchains.py
ot.py
parallelsort.py
pseudoinverse.py
ridgeregression.py
secretsanta.py
sha3.py
sort.py
unanimous.py
mpyc/README.md
mpyc/__init__.py
mpyc/__main__.py
mpyc/asyncoro.py
mpyc/finfields.py
mpyc/fingroups.py
mpyc/gfpx.py
mpyc/gmpy.py
mpyc/mpctools.py
mpyc/numpy.py
mpyc/random.py
mpyc/runtime.py
mpyc/secgroups.py
mpyc/seclists.py
mpyc/sectypes.py
mpyc/statistics.py
mpyc/thresha.py
mpycweb/__init__.py
mpycweb/benches/__init__.py
mpycweb/patches.py
mpycweb/proxy.py
mpycweb/run_mpc.py
mpycweb/transport.py
startup/__init__.py
startup/test.py
mpyc_web-0.7.0.dist-info/LICENSE
mpyc_web-0.7.0.dist-info/METADATA
mpyc_web-0.7.0.dist-info/WHEEL
mpyc_web-0.7.0.dist-info/RECORD
