Metadata-Version: 2.1
Name: mpyc-web
Version: 0.7.0
Summary: MPyC for Multiparty Computation in Python for the Web
Author: Emil Nikolov
Author-email: eenikolov@proton.me
Requires-Python: >=3.12,<4.0
Classifier: Programming Language :: Python :: 3
Classifier: Programming Language :: Python :: 3.12
Provides-Extra: dev-tools
Requires-Dist: humanize (>=4.8.0,<5.0.0)
Requires-Dist: numpy (>=1.25.2,<2.0.0)
Requires-Dist: pyyaml (>=6.0.1,<7.0.0)
Requires-Dist: rich (>=13.5.3,<14.0.0)
